CHANGES.rst
LICENSE.GPL
MANIFEST.in
README.rst
buildout.cfg
requirements.txt
setup.py
docs/LICENSE.GPL
docs/LICENSE.txt
plone/__init__.py
plone.app.changeownership.egg-info/PKG-INFO
plone.app.changeownership.egg-info/SOURCES.txt
plone.app.changeownership.egg-info/dependency_links.txt
plone.app.changeownership.egg-info/entry_points.txt
plone.app.changeownership.egg-info/namespace_packages.txt
plone.app.changeownership.egg-info/not-zip-safe
plone.app.changeownership.egg-info/requires.txt
plone.app.changeownership.egg-info/top_level.txt
plone/app/__init__.py
plone/app/changeownership/__init__.py
plone/app/changeownership/change_owner.py
plone/app/changeownership/changeowner.pt
plone/app/changeownership/configure.zcml
plone/app/changeownership/rebuild_i18n.sh
plone/app/changeownership/setuphandlers.py
plone/app/changeownership/testing.py
plone/app/changeownership/Extensions/install.py
plone/app/changeownership/locales/plone.app.changeownership-manual.pot
plone/app/changeownership/locales/plone.app.changeownership.pot
plone/app/changeownership/locales/de/LC_MESSAGES/plone.app.changeownership.po
plone/app/changeownership/locales/it/LC_MESSAGES/plone.app.changeownership.po
plone/app/changeownership/locales/nl/LC_MESSAGES/plone.app.changeownership.po
plone/app/changeownership/locales/zh_CN/LC_MESSAGES/plone.app.changeownership.po
plone/app/changeownership/profiles/default/controlpanel.xml
plone/app/changeownership/profiles/default/metadata.xml
plone/app/changeownership/profiles/default/rolemap.xml
plone/app/changeownership/profiles/uninstall/controlpanel.xml
plone/app/changeownership/tests/__init__.py
plone/app/changeownership/tests/test_change_ownership.py